utils/__init__.py
utils/constants.py
xquantipy/__init__.py
xquantipy/constants.py
xquantipy/economics/__init__.py
xquantipy/economics/analysis.py
xquantipy/economics/macro.py
xquantipy/fetcher/__init__.py
xquantipy/fetcher/scraper.py
xquantipy/stocks/__init__.py
xquantipy/stocks/analysis.py
xquantipy/stocks/ticker.py
xquantipy-0.2.5.dist-info/LICENSE.md
xquantipy-0.2.5.dist-info/METADATA
xquantipy-0.2.5.dist-info/WHEEL
xquantipy-0.2.5.dist-info/top_level.txt
xquantipy-0.2.5.dist-info/RECORD
