Metadata-Version: 2.1
Name: xquantipy
Version: 0.2.5
Summary: Module for financial analysis
Author: Sai Charan Vadakapur
Platform: any
Classifier: License :: OSI Approved :: MIT License
Classifier: Operating System :: OS Independent
Classifier: Programming Language :: Python :: 3
Classifier: Intended Audience :: Developers
License-File: LICENSE.md
Requires-Dist: beautifulsoup4
Requires-Dist: cloudscraper
Requires-Dist: matplotlib
Requires-Dist: numpy
Requires-Dist: pandas
Requires-Dist: pipreqs
Requires-Dist: plotly
Requires-Dist: pytest
Requires-Dist: python-dateutil
Requires-Dist: Requests
Requires-Dist: seaborn
Requires-Dist: setuptools
Requires-Dist: statsmodels
Requires-Dist: yfinance
